Metadata-Version: 2.1
Name: talon_one
Version: 6.1.1
Summary: Talon.One Python SDK
Home-page: https://github.com/talon-one/talon_one.py/
Author: Talon.One GmbH
Author-email: devs@talon.one
License: MIT
Keywords: OpenAPI,OpenAPI-Generator,Talon.One API
License-File: LICENSE
Requires-Dist: urllib3 >=1.15
Requires-Dist: six >=1.10
Requires-Dist: certifi
Requires-Dist: python-dateutil
